dockit/__init__.py
dockit/dockit.py
dockit/test.py
dockit-0.1.8.data/scripts/dockit
dockit-0.1.8.dist-info/METADATA
dockit-0.1.8.dist-info/WHEEL
dockit-0.1.8.dist-info/top_level.txt
dockit-0.1.8.dist-info/RECORD
