Metadata-Version: 2.1
Name: dockit
Version: 0.1.8
Summary: Fuzzy the current location to pull all the submodules and specify the project if required. To launch, close and execute container with docker-compose and its relative services without change the directory.
Home-page: https://github.com/Ron-Chang/dockit.git
Author: Ron Chang
Author-email: ron.hsien.chang@gmail.com
License: MIT
Platform: UNKNOWN
Requires-Python: >=3.6
